Metadata-Version: 2.1
Name: bpnsdata
Version: 0.2.0
Summary: A package to add marine environmental data to a geopandas dataframe
Author: Clea Parcerisas
Author-email: cleaparcerisas@gmail.com
Requires-Python: >=3.10
Classifier: Programming Language :: Python :: 3
Classifier: Programming Language :: Python :: 3.10
Classifier: Programming Language :: Python :: 3.11
Classifier: Programming Language :: Python :: 3.12
Requires-Dist: OWSLib (>=0.30.0,<0.31.0)
Requires-Dist: contextily (>=1.6.0,<2.0.0)
Requires-Dist: erddapy (>=2.2.0,<3.0.0)
Requires-Dist: geopandas (>=0.14.3,<0.15.0)
Requires-Dist: netCDF4 (>=1.6.5,<2.0.0)
Requires-Dist: rioxarray (>=0.15.3,<0.16.0)
Requires-Dist: skyfield (>=1.48,<2.0)
Requires-Dist: tqdm (>=4.66.2,<5.0.0)
